quillai/__init__.py
quillai/client.py
quillai-0.1.2.dist-info/licenses/LICENSE
quillai-0.1.2.dist-info/METADATA
quillai-0.1.2.dist-info/WHEEL
quillai-0.1.2.dist-info/top_level.txt
quillai-0.1.2.dist-info/RECORD
