Metadata-Version: 2.4
Name: quillai
Version: 0.1.2
Summary: Python interface for Quill Express API - AI-powered financial data processing
Home-page: https://github.com/quillai/quill-python
Author: Quill AI
Author-email: Quill AI <support@quillai.com>
License: MIT
Project-URL: Homepage, https://github.com/quillai/quill-python
Project-URL: Repository, https://github.com/quillai/quill-python
Project-URL: Documentation, https://github.com/quillai/quill-python
Project-URL: Issues, https://github.com/quillai/quill-python/issues
Classifier: Development Status :: 3 - Alpha
Classifier: Intended Audience :: Financial and Insurance Industry
Classifier: License :: OSI Approved :: MIT License
Classifier: Operating System :: OS Independent
Classifier: Programming Language :: Python :: 3
Classifier: Programming Language :: Python :: 3.8
Classifier: Programming Language :: Python :: 3.9
Classifier: Programming Language :: Python :: 3.10
Classifier: Programming Language :: Python :: 3.11
Classifier: Programming Language :: Python :: 3.12
Requires-Python: >=3.8
License-File: LICENSE
Requires-Dist: pandas>=1.3.0
Requires-Dist: requests>=2.25.0
Provides-Extra: dev
Requires-Dist: pytest>=6.0; extra == "dev"
Requires-Dist: black>=21.0; extra == "dev"
Requires-Dist: flake8>=3.8; extra == "dev"
Requires-Dist: mypy>=0.910; extra == "dev"
Dynamic: author
Dynamic: home-page
Dynamic: license-file
Dynamic: requires-python
